pda-0.3.0.2.dist-info/WHEEL
pda-0.3.0.2.dist-info/metadata.json
pda-0.3.0.2.dist-info/RECORD
pda-0.3.0.2.dist-info/DESCRIPTION.rst
pda-0.3.0.2.dist-info/zip-safe
pda-0.3.0.2.dist-info/entry_points.txt
pda-0.3.0.2.dist-info/top_level.txt
pda-0.3.0.2.dist-info/METADATA
pda/control.py
pda/__init__.py
pda/utils.py
pda/listdb/Config.py
pda/listdb/ListDB.py
pda/listdb/__init__.py
