Metadata-Version: 2.0
Name: pda
Version: 0.3.0.2
Summary: A command line todo list manager
Home-page: https://github.com/keenhenry/pda
Author: Henry Huang
Author-email: UNKNOWN
License: BSD
Keywords: command line todo list TODO todolist
Platform: any
Classifier: Development Status :: 4 - Beta
Classifier: License :: OSI Approved :: BSD License
Classifier: Intended Audience :: Developers
Classifier: Operating System :: OS Independent
Classifier: Programming Language :: Python :: 2
Classifier: Programming Language :: Python :: 2.6
Classifier: Programming Language :: Python :: 2.7
Classifier: Programming Language :: Python :: 3
Classifier: Programming Language :: Python :: 3.3
Classifier: Programming Language :: Python :: 3.4
Requires-Dist: requests
